mk_badge/VERSION
mk_badge/__init__.py
mk_badge/main.py
mk_badge-1.0.2.dist-info/LICENSE
mk_badge-1.0.2.dist-info/METADATA
mk_badge-1.0.2.dist-info/WHEEL
mk_badge-1.0.2.dist-info/entry_points.txt
mk_badge-1.0.2.dist-info/top_level.txt
mk_badge-1.0.2.dist-info/RECORD
