Metadata-Version: 2.1
Name: mk-badge
Version: 1.0.2
Summary: Makes badges like the ones made by travis-ci to show the status of a build
Home-page: https://gitlab.com/NamingThingsIsHard/media_tools/mk_badge
Author: LoveIsGrief
Author-email: loveisgrief@tuta.io
Project-URL: Bug Tracker, https://gitlab.com/NamingThingsIsHard/media_tools/mk_badge/issues
Classifier: Programming Language :: Python :: 3
Classifier: License :: OSI Approved :: GNU General Public License v3 (GPLv3)
Classifier: Operating System :: POSIX :: Linux
License-File: LICENSE
Requires-Dist: pycairo
